verse/ql/__init__.py
verse/ql/_parser_listener.py
verse/ql/_ql_parser.py
verse/ql/exceptions.py
verse/ql/generated/VerseQLLexer.interp
verse/ql/generated/VerseQLLexer.py
verse/ql/generated/VerseQLLexer.tokens
verse/ql/generated/VerseQLParser.interp
verse/ql/generated/VerseQLParser.py
verse/ql/generated/VerseQLParser.tokens
verse/ql/generated/VerseQLParserListener.py
verse/ql/grammar/VerseQLLexer.g4
verse/ql/grammar/VerseQLParser.g4
verse/ql/py.typed
verse_ql-0.0.27.dist-info/LICENSE
verse_ql-0.0.27.dist-info/METADATA
verse_ql-0.0.27.dist-info/WHEEL
verse_ql-0.0.27.dist-info/RECORD
