Metadata-Version: 2.1
Name: verse-ql
Version: 0.0.27
Summary: Verse QL
Home-page: https://github.com/rapidverse/verse
License: MIT
Keywords: verse,ql,verseql
Author: Verse
Author-email: admin@rapidverse.com
Requires-Python: >=3.9
Classifier: License :: OSI Approved :: MIT License
Classifier: Programming Language :: Python :: 3
Classifier: Programming Language :: Python :: 3.9
Classifier: Programming Language :: Python :: 3.10
Classifier: Programming Language :: Python :: 3.11
Classifier: Programming Language :: Python :: 3.12
Requires-Dist: antlr4-python3-runtime (>=4.13.0)
Project-URL: Documentation, https://github.com/rapidverse/verse
Project-URL: Repository, https://github.com/rapidverse/verse
